src/__init__.py
src/__main__.py
src/config.py
src/main.py
src/routes.py
src/server.py
src/test_routes.py
src/types_helper.py
src/gateway/__init__.py
src/gateway/event_buffer.py
src/gateway/event_filter.py
src/gateway/manager.py
src/security/__init__.py
src/security/confirmation.py
src/security/policy.py
src/tools/__init__.py
src/tools/advanced_operations.py
src/tools/audit_logs.py
src/tools/auto_moderation.py
src/tools/basic.py
src/tools/bulk_delete.py
src/tools/channels.py
src/tools/content.py
src/tools/forum.py
src/tools/guild_templates.py
src/tools/messaging.py
src/tools/moderation.py
src/tools/raw_rest.py
src/tools/roles.py
src/tools/scheduled_events.py
src/tools/server.py
src/tools/slash_commands.py
src/tools/soundboard.py
src/tools/stage_instances.py
src/tools/stickers.py
src/tools/threads.py
src/tools/users.py
src/tools/voice.py
src/tools/webhooks.py
src/tools/welcome_screen.py
discord_py_suite-0.1.0.dist-info/METADATA
discord_py_suite-0.1.0.dist-info/WHEEL
discord_py_suite-0.1.0.dist-info/entry_points.txt
discord_py_suite-0.1.0.dist-info/RECORD
