Metadata-Version: 2.4
Name: discord-py-suite
Version: 0.1.0
Summary: Discord MCP Server - Complete Discord integration for Model Context Protocol
Author-email: sachicali <calingasan.vinchi@gmail.com>
Requires-Python: >=3.11
Requires-Dist: aiohttp>=3.9.0
Requires-Dist: discord-py>=2.6.3
Requires-Dist: fastmcp>=2.12.0
Requires-Dist: loguru>=0.7.3
Requires-Dist: py-cord>=2.6.1
Requires-Dist: pydantic>=2.11.7
Requires-Dist: python-dotenv>=1.1.1
Provides-Extra: dev
Requires-Dist: black>=23.0.0; extra == 'dev'
Requires-Dist: mypy>=1.0.0; extra == 'dev'
Requires-Dist: pytest-asyncio>=0.21.0; extra == 'dev'
Requires-Dist: pytest-cov>=4.0.0; extra == 'dev'
Requires-Dist: pytest>=7.0.0; extra == 'dev'
Requires-Dist: ruff>=0.1.0; extra == 'dev'
